Metadata-Version: 2.1
Name: litstrings-cli
Version: 0.0.4
Summary: A command line interface for LitStrings
Home-page: https://litstrings.info
Author: Iridium Intelligence
Author-email: litstrings@iridiumintel.com
License: GPLv2
Keywords: translation,localization,internationalization
Platform: UNKNOWN
Classifier: Programming Language :: Python
Classifier: Programming Language :: Python :: 2
Classifier: Programming Language :: Python :: 2.7
Classifier: Programming Language :: Python :: 3.5
Classifier: Programming Language :: Python :: 3.6
Classifier: Programming Language :: Python :: 3.7
Classifier: Programming Language :: Python :: 3.8
Requires-Python: >=2.7,!=3.0.*,!=3.1.*,!=3.2.*,!=3.3.*,<3.9
